Metadata-Version: 2.0
Name: yunpipe2
Version: 0.0.0
Summary: An Automatic tool for setting up your image processing work flow on the cloud
Home-page: https://github.com/nujhedtozu/yunpipe
Author: Deh-Jun Tzou
Author-email: junior.tzou@gmail.com
License: Apache v2.0
Platform: UNKNOWN
Requires-Dist: Haikunator
Requires-Dist: boto3
